qin_plot/__init__.py
qin_plot/composition.py
qin_plot/figures.py
qin_plot-1.0.5.dist-info/LICENSE
qin_plot-1.0.5.dist-info/METADATA
qin_plot-1.0.5.dist-info/WHEEL
qin_plot-1.0.5.dist-info/top_level.txt
qin_plot-1.0.5.dist-info/RECORD
